kani/__init__.py
kani/__main__.py
kani/_cli.py
kani/_optional.py
kani/_version.py
kani/ai_function.py
kani/exceptions.py
kani/internal.py
kani/json_schema.py
kani/kani.py
kani/mcp.py
kani/models.py
kani/streaming.py
kani/engines/__init__.py
kani/engines/base.py
kani/engines/mixins.py
kani/engines/anthropic/__init__.py
kani/engines/anthropic/engine.py
kani/engines/anthropic/mm_tokens.py
kani/engines/anthropic/model_constants.py
kani/engines/anthropic/parts.py
kani/engines/google/__init__.py
kani/engines/google/engine.py
kani/engines/google/mm_tokens.py
kani/engines/google/model_constants.py
kani/engines/huggingface/__init__.py
kani/engines/huggingface/__main__.py
kani/engines/huggingface/base.py
kani/engines/huggingface/chat_template_pipeline.py
kani/engines/huggingface/llama2.py
kani/engines/llamacpp/__init__.py
kani/engines/llamacpp/base.py
kani/engines/openai/__init__.py
kani/engines/openai/engine.py
kani/engines/openai/function_calling.py
kani/engines/openai/mm_tokens.py
kani/engines/openai/model_constants.py
kani/engines/openai/translation.py
kani/engines/openai/utils.py
kani/model_specific/README.md
kani/model_specific/__init__.py
kani/model_specific/base.py
kani/model_specific/deepseek.py
kani/model_specific/gpt_oss.py
kani/model_specific/json.py
kani/model_specific/llama2.py
kani/model_specific/llama3.py
kani/model_specific/mistral.py
kani/model_specific/qwen3.py
kani/parts/__init__.py
kani/parts/reasoning.py
kani/parts/text.py
kani/prompts/__init__.py
kani/prompts/base.py
kani/prompts/docutils.py
kani/prompts/examples.py
kani/prompts/pipeline.py
kani/prompts/steps.py
kani/prompts/types.py
kani/utils/__init__.py
kani/utils/cli.py
kani/utils/huggingface.py
kani/utils/message_formatters.py
kani/utils/saveload.py
kani/utils/typing.py
kani/utils/warnings.py
kani-1.8.0.dist-info/METADATA
kani-1.8.0.dist-info/WHEEL
kani-1.8.0.dist-info/entry_points.txt
kani-1.8.0.dist-info/licenses/LICENSE
kani-1.8.0.dist-info/RECORD
