Metadata-Version: 2.4
Name: kani
Version: 1.8.0
Summary: kani (カニ) is a lightweight and highly hackable framework for chat-based language models with tool usage/function calling.
Project-URL: Homepage, https://github.com/zhudotexe/kani
Project-URL: Bug Tracker, https://github.com/zhudotexe/kani/issues
Author-email: Andrew Zhu <andrew@zhu.codes>, Liam Dugan <ldugan@seas.upenn.edu>, Alyssa Hwang <ahwang16@seas.upenn.edu>
License: MIT License
License-File: LICENSE
Classifier: Development Status :: 4 - Beta
Classifier: Intended Audience :: Science/Research
Classifier: License :: OSI Approved :: MIT License
Classifier: Operating System :: OS Independent
Classifier: Programming Language :: Python :: 3
Classifier: Topic :: Scientific/Engineering :: Artificial Intelligence
Requires-Python: >=3.10
Requires-Dist: pydantic<3.0.0,>=2.0.0
Provides-Extra: all
Requires-Dist: anthropic<1.0.0,>=0.27.0; extra == 'all'
Requires-Dist: google-genai<2.0.0,>=1.0.0; extra == 'all'
Requires-Dist: huggingface-hub; extra == 'all'
Requires-Dist: kani-ext-vllm; extra == 'all'
Requires-Dist: kani-multimodal-core<2.0.0; extra == 'all'
Requires-Dist: llama-cpp-python<1.0.0,>=0.2.0; extra == 'all'
Requires-Dist: mcp<2.0.0,>=1.15.0; extra == 'all'
Requires-Dist: openai<3.0.0,>=1.26.0; extra == 'all'
Requires-Dist: protobuf; extra == 'all'
Requires-Dist: sentencepiece<1.0.0,>=0.1.99; extra == 'all'
Requires-Dist: tiktoken<1.0.0,>=0.7.0; extra == 'all'
Requires-Dist: transformers<5.0.0,>=4.28.0; extra == 'all'
Requires-Dist: transformers<5.0.0,>=4.56.1; extra == 'all'
Provides-Extra: anthropic
Requires-Dist: anthropic<1.0.0,>=0.27.0; extra == 'anthropic'
Provides-Extra: cpp
Requires-Dist: huggingface-hub; extra == 'cpp'
Requires-Dist: llama-cpp-python<1.0.0,>=0.2.0; extra == 'cpp'
Requires-Dist: sentencepiece<1.0.0,>=0.1.99; extra == 'cpp'
Provides-Extra: google
Requires-Dist: google-genai<2.0.0,>=1.0.0; extra == 'google'
Provides-Extra: huggingface
Requires-Dist: huggingface-hub; extra == 'huggingface'
Requires-Dist: transformers<5.0.0,>=4.28.0; extra == 'huggingface'
Provides-Extra: llama
Requires-Dist: protobuf; extra == 'llama'
Requires-Dist: sentencepiece<1.0.0,>=0.1.99; extra == 'llama'
Provides-Extra: mcp
Requires-Dist: mcp<2.0.0,>=1.15.0; extra == 'mcp'
Provides-Extra: multimodal
Requires-Dist: kani-multimodal-core<2.0.0; extra == 'multimodal'
Requires-Dist: transformers<5.0.0,>=4.56.1; extra == 'multimodal'
Provides-Extra: openai
Requires-Dist: openai<3.0.0,>=1.26.0; extra == 'openai'
Requires-Dist: tiktoken<1.0.0,>=0.7.0; extra == 'openai'
Provides-Extra: vllm
Requires-Dist: kani-ext-vllm; extra == 'vllm'
